{
  "cli": {
  	"version": ">= 10.1.1"
  	},
  	"build": {
  	"development": {
  		"developmentClient": true,
  		"distribution": "internal"
  	},
  	"preview": {
  		"ios": {
  			"simulator": true
  		},
  		"android": {
  			"buildType": "apk"
  		},
  		"channel": "preview"
  	},
  	"production": {
  		"channel": "preview"
  	},
	"development-sim": {
		"distribution": "internal",
		"ios": {
			"simulator": true
		},
		"android": {
  			"buildType": "apk"
  		}
	}
  	},
  	"submit": {
  	"production": {}
  }
}
